{
	"implicitPatches": {
		"composables": [
			{
				"blendingFactor": 2.0,
				"composableA": {
					"blendingFactor": 2.0,
					"composableA": {
						"blendingFactor": 2.0,
						"composableA": {
							"blendingFactor": 2.0,
							"composableA": {
								"blendingFactor": 2.0,
								"composableA": {
									"blendingFactor": 2.0,
									"composableA": {
										"blendingFactor": 6.300000190734863,
										"composableA": {
											"blendingFactor": 6.300000190734863,
											"composableA": {
												"blendingFactor": 6.300000190734863,
												"composableA": {
													"blendingFactor": 3.1000001430511475,
													"composableA": {
														"blendingFactor": 3.1000001430511475,
														"composableA": {
															"blendingFactor": 2.299999952316284,
															"composableA": {
																"blendingFactor": 10.0,
																"composableA": {
																	"blendingFactor": 10.0,
																	"composableA": {
																		"densityValue": 0.75,
																		"dimensions": {
																			"x": 100.0,
																			"y": 100.0,
																			"z": 30.0
																		},
																		"index": 43,
																		"material": "DIRT",
																		"mirrored": false,
																		"name": "Heightmap",
																		"optionalCurve": {
																			"closed": false,
																			"points": []
																		},
																		"position": {
																			"x": 0.0,
																			"y": 0.0,
																			"z": 0.0
																		},
																		"shape": "Implicit_Heightmap",
																		"sigmaValue": -1.0,
																		"supportDimensions": {
																			"x": 0.0,
																			"y": 0.0,
																			"z": 0.0
																		},
																		"type": "primitive"
																	},
																	"composableB": {
																		"composableA": {
																			"densityValue": 1.5,
																			"dimensions": {
																				"x": 15.600000381469727,
																				"y": 15.100000381469727,
																				"z": 21.399999618530273
																			},
																			"index": 42,
																			"material": "ROCK",
																			"mirrored": false,
																			"name": "Block",
																			"optionalCurve": {
																				"closed": false,
																				"points": []
																			},
																			"position": {
																				"x": 39.546142578125,
																				"y": 29.243640899658203,
																				"z": 0.0
																			},
																			"shape": "Block",
																			"sigmaValue": 5.0,
																			"supportDimensions": {
																				"x": 0.0,
																				"y": 0.0,
																				"z": 0.0
																			},
																			"type": "primitive"
																		},
																		"distortion": {
																			"x": 0.0,
																			"y": 0.0,
																			"z": 0.0
																		},
																		"index": 41,
																		"mirrored": false,
																		"name": "",
																		"noise": {
																			"x": 0.0,
																			"y": 0.0,
																			"z": 0.0
																		},
																		"optionalCurve": {
																			"closed": false,
																			"points": []
																		},
																		"rotation": {
																			"x": 0.0,
																			"y": 0.0,
																			"z": 0.0
																		},
																		"scale": {
																			"x": 1.0,
																			"y": 1.0,
																			"z": 1.0
																		},
																		"spreadFactor": 0.0,
																		"translation": {
																			"x": 0.0,
																			"y": 0.0,
																			"z": 3.0600085258483887
																		},
																		"type": "unary"
																	},
																	"index": 40,
																	"mirrored": false,
																	"name": "Blend",
																	"operator": "Blend",
																	"optionalCurve": {
																		"closed": false,
																		"points": []
																	},
																	"positionalB": "FIXED_POS",
																	"type": "compose",
																	"useIntersection": false
																},
																"composableB": {
																	"composableA": {
																		"densityValue": 1.5,
																		"dimensions": {
																			"x": 15.600000381469727,
																			"y": 15.100000381469727,
																			"z": 21.399999618530273
																		},
																		"index": 39,
																		"material": "ROCK",
																		"mirrored": false,
																		"name": "Block",
																		"optionalCurve": {
																			"closed": false,
																			"points": []
																		},
																		"position": {
																			"x": 40.75227737426758,
																			"y": 47.2297248840332,
																			"z": 0.0
																		},
																		"shape": "Block",
																		"sigmaValue": 5.0,
																		"supportDimensions": {
																			"x": 0.0,
																			"y": 0.0,
																			"z": 0.0
																		},
																		"type": "primitive"
																	},
																	"distortion": {
																		"x": 0.0,
																		"y": 0.0,
																		"z": 0.0
																	},
																	"index": 38,
																	"mirrored": false,
																	"name": "",
																	"noise": {
																		"x": 0.0,
																		"y": 0.0,
																		"z": 0.0
																	},
																	"optionalCurve": {
																		"closed": false,
																		"points": []
																	},
																	"rotation": {
																		"x": 0.0,
																		"y": 0.0,
																		"z": 0.0
																	},
																	"scale": {
																		"x": 1.0,
																		"y": 1.0,
																		"z": 1.0
																	},
																	"spreadFactor": 0.0,
																	"translation": {
																		"x": 0.0,
																		"y": 0.0,
																		"z": 3.1283493041992188
																	},
																	"type": "unary"
																},
																"index": 37,
																"mirrored": false,
																"name": "Blend",
																"operator": "Blend",
																"optionalCurve": {
																	"closed": false,
																	"points": []
																},
																"positionalB": "FIXED_POS",
																"type": "compose",
																"useIntersection": false
															},
															"composableB": {
																"composableA": {
																	"densityValue": 1.5,
																	"dimensions": {
																		"x": 15.600000381469727,
																		"y": 15.100000381469727,
																		"z": 21.399999618530273
																	},
																	"index": 36,
																	"material": "ROCK",
																	"mirrored": false,
																	"name": "Block",
																	"optionalCurve": {
																		"closed": false,
																		"points": []
																	},
																	"position": {
																		"x": 39.07487869262695,
																		"y": 12.005976676940918,
																		"z": 0.0
																	},
																	"shape": "Block",
																	"sigmaValue": 5.0,
																	"supportDimensions": {
																		"x": 0.0,
																		"y": 0.0,
																		"z": 0.0
																	},
																	"type": "primitive"
																},
																"distortion": {
																	"x": 0.0,
																	"y": 0.0,
																	"z": 0.0
																},
																"index": 35,
																"mirrored": false,
																"name": "",
																"noise": {
																	"x": 0.0,
																	"y": 0.0,
																	"z": 0.0
																},
																"optionalCurve": {
																	"closed": false,
																	"points": []
																},
																"rotation": {
																	"x": 0.0,
																	"y": 0.0,
																	"z": 0.0
																},
																"scale": {
																	"x": 1.0,
																	"y": 1.0,
																	"z": 1.0
																},
																"spreadFactor": 0.0,
																"translation": {
																	"x": 0.0,
																	"y": 0.0,
																	"z": 2.923046112060547
																},
																"type": "unary"
															},
															"index": 34,
															"mirrored": false,
															"name": "Blend",
															"operator": "Blend",
															"optionalCurve": {
																"closed": false,
																"points": []
															},
															"positionalB": "FIXED_POS",
															"type": "compose",
															"useIntersection": false
														},
														"composableB": {
															"composableA": {
																"densityValue": 1.5,
																"dimensions": {
																	"x": 15.600000381469727,
																	"y": 15.100000381469727,
																	"z": 21.399999618530273
																},
																"index": 33,
																"material": "ROCK",
																"mirrored": false,
																"name": "Block",
																"optionalCurve": {
																	"closed": false,
																	"points": []
																},
																"position": {
																	"x": 45.38405227661133,
																	"y": 66.01370239257813,
																	"z": 0.0
																},
																"shape": "Block",
																"sigmaValue": 5.0,
																"supportDimensions": {
																	"x": 0.0,
																	"y": 0.0,
																	"z": 0.0
																},
																"type": "primitive"
															},
															"distortion": {
																"x": 0.0,
																"y": 0.0,
																"z": 0.0
															},
															"index": 32,
															"mirrored": false,
															"name": "",
															"noise": {
																"x": 0.0,
																"y": 0.0,
																"z": 0.0
															},
															"optionalCurve": {
																"closed": false,
																"points": []
															},
															"rotation": {
																"x": 0.0,
																"y": 0.0,
																"z": 0.0
															},
															"scale": {
																"x": 1.0,
																"y": 1.0,
																"z": 1.0
															},
															"spreadFactor": 0.0,
															"translation": {
																"x": 0.0,
																"y": 0.0,
																"z": 3.245694160461426
															},
															"type": "unary"
														},
														"index": 31,
														"mirrored": false,
														"name": "Blend",
														"operator": "Blend",
														"optionalCurve": {
															"closed": false,
															"points": []
														},
														"positionalB": "FIXED_POS",
														"type": "compose",
														"useIntersection": false
													},
													"composableB": {
														"composableA": {
															"densityValue": 1.5,
															"dimensions": {
																"x": 15.600000381469727,
																"y": 15.100000381469727,
																"z": 21.399999618530273
															},
															"index": 30,
															"material": "ROCK",
															"mirrored": false,
															"name": "Block",
															"optionalCurve": {
																"closed": false,
																"points": []
															},
															"position": {
																"x": 27.92364501953125,
																"y": 66.03099060058594,
																"z": 0.0
															},
															"shape": "Block",
															"sigmaValue": 5.0,
															"supportDimensions": {
																"x": 0.0,
																"y": 0.0,
																"z": 0.0
															},
															"type": "primitive"
														},
														"distortion": {
															"x": 0.0,
															"y": 0.0,
															"z": 0.0
														},
														"index": 29,
														"mirrored": false,
														"name": "",
														"noise": {
															"x": 0.0,
															"y": 0.0,
															"z": 0.0
														},
														"optionalCurve": {
															"closed": false,
															"points": []
														},
														"rotation": {
															"x": 0.0,
															"y": 0.0,
															"z": 0.0
														},
														"scale": {
															"x": 1.0,
															"y": 1.0,
															"z": 1.0
														},
														"spreadFactor": 0.0,
														"translation": {
															"x": 0.0,
															"y": 0.0,
															"z": 3.292287588119507
														},
														"type": "unary"
													},
													"index": 28,
													"mirrored": false,
													"name": "Blend",
													"operator": "Blend",
													"optionalCurve": {
														"closed": false,
														"points": []
													},
													"positionalB": "FIXED_POS",
													"type": "compose",
													"useIntersection": false
												},
												"composableB": {
													"composableA": {
														"densityValue": 1.5,
														"dimensions": {
															"x": 15.600000381469727,
															"y": 15.100000381469727,
															"z": 21.399999618530273
														},
														"index": 27,
														"material": "ROCK",
														"mirrored": false,
														"name": "Block",
														"optionalCurve": {
															"closed": false,
															"points": []
														},
														"position": {
															"x": 61.7876091003418,
															"y": 78.69087982177734,
															"z": 0.0
														},
														"shape": "Block",
														"sigmaValue": 5.0,
														"supportDimensions": {
															"x": 0.0,
															"y": 0.0,
															"z": 0.0
														},
														"type": "primitive"
													},
													"distortion": {
														"x": 0.0,
														"y": 0.0,
														"z": 0.0
													},
													"index": 26,
													"mirrored": false,
													"name": "",
													"noise": {
														"x": 0.0,
														"y": 0.0,
														"z": 0.0
													},
													"optionalCurve": {
														"closed": false,
														"points": []
													},
													"rotation": {
														"x": 0.0,
														"y": 0.0,
														"z": 0.0
													},
													"scale": {
														"x": 1.0,
														"y": 1.0,
														"z": 1.0
													},
													"spreadFactor": 0.0,
													"translation": {
														"x": 0.0,
														"y": 0.0,
														"z": 2.6064634323120117
													},
													"type": "unary"
												},
												"index": 25,
												"mirrored": false,
												"name": "Blend",
												"operator": "Blend",
												"optionalCurve": {
													"closed": false,
													"points": []
												},
												"positionalB": "FIXED_POS",
												"type": "compose",
												"useIntersection": false
											},
											"composableB": {
												"composableA": {
													"densityValue": 1.5,
													"dimensions": {
														"x": 15.600000381469727,
														"y": 15.100000381469727,
														"z": 21.399999618530273
													},
													"index": 24,
													"material": "ROCK",
													"mirrored": false,
													"name": "Block",
													"optionalCurve": {
														"closed": false,
														"points": []
													},
													"position": {
														"x": 46.5413703918457,
														"y": 38.81599044799805,
														"z": 0.0
													},
													"shape": "Block",
													"sigmaValue": 5.0,
													"supportDimensions": {
														"x": 0.0,
														"y": 0.0,
														"z": 0.0
													},
													"type": "primitive"
												},
												"distortion": {
													"x": 0.0,
													"y": 0.0,
													"z": 0.0
												},
												"index": 23,
												"mirrored": false,
												"name": "",
												"noise": {
													"x": 0.0,
													"y": 0.0,
													"z": 0.0
												},
												"optionalCurve": {
													"closed": false,
													"points": []
												},
												"rotation": {
													"x": 0.0,
													"y": 0.0,
													"z": 0.0
												},
												"scale": {
													"x": 1.0,
													"y": 1.0,
													"z": 1.0
												},
												"spreadFactor": 0.0,
												"translation": {
													"x": 0.0,
													"y": 0.0,
													"z": 3.3592376708984375
												},
												"type": "unary"
											},
											"index": 22,
											"mirrored": false,
											"name": "Blend",
											"operator": "Blend",
											"optionalCurve": {
												"closed": false,
												"points": []
											},
											"positionalB": "FIXED_POS",
											"type": "compose",
											"useIntersection": true
										},
										"composableB": {
											"composableA": {
												"densityValue": 1.5,
												"dimensions": {
													"x": 15.600000381469727,
													"y": 15.100000381469727,
													"z": 21.399999618530273
												},
												"index": 21,
												"material": "ROCK",
												"mirrored": false,
												"name": "Block",
												"optionalCurve": {
													"closed": false,
													"points": []
												},
												"position": {
													"x": 58.13222885131836,
													"y": 29.986347198486328,
													"z": 0.0
												},
												"shape": "Block",
												"sigmaValue": 5.0,
												"supportDimensions": {
													"x": 0.0,
													"y": 0.0,
													"z": 0.0
												},
												"type": "primitive"
											},
											"distortion": {
												"x": 0.0,
												"y": 0.0,
												"z": 0.0
											},
											"index": 20,
											"mirrored": false,
											"name": "",
											"noise": {
												"x": 0.0,
												"y": 0.0,
												"z": 0.0
											},
											"optionalCurve": {
												"closed": false,
												"points": []
											},
											"rotation": {
												"x": 0.0,
												"y": 0.0,
												"z": 0.0
											},
											"scale": {
												"x": 1.0,
												"y": 1.0,
												"z": 1.0
											},
											"spreadFactor": 0.0,
											"translation": {
												"x": 0.0,
												"y": 0.0,
												"z": 2.8058619499206543
											},
											"type": "unary"
										},
										"index": 19,
										"mirrored": false,
										"name": "One Side Blend",
										"operator": "One_side_blend",
										"optionalCurve": {
											"closed": false,
											"points": []
										},
										"positionalB": "FIXED_POS",
										"type": "compose",
										"useIntersection": true
									},
									"composableB": {
										"composableA": {
											"densityValue": 1.5,
											"dimensions": {
												"x": 15.600000381469727,
												"y": 15.100000381469727,
												"z": 21.399999618530273
											},
											"index": 18,
											"material": "ROCK",
											"mirrored": false,
											"name": "Block",
											"optionalCurve": {
												"closed": false,
												"points": []
											},
											"position": {
												"x": 75.7534408569336,
												"y": 62.38424301147461,
												"z": 0.0
											},
											"shape": "Block",
											"sigmaValue": 5.0,
											"supportDimensions": {
												"x": 0.0,
												"y": 0.0,
												"z": 0.0
											},
											"type": "primitive"
										},
										"distortion": {
											"x": 0.0,
											"y": 0.0,
											"z": 0.0
										},
										"index": 17,
										"mirrored": false,
										"name": "",
										"noise": {
											"x": 0.0,
											"y": 0.0,
											"z": 0.0
										},
										"optionalCurve": {
											"closed": false,
											"points": []
										},
										"rotation": {
											"x": 0.0,
											"y": 0.0,
											"z": 0.0
										},
										"scale": {
											"x": 1.0,
											"y": 1.0,
											"z": 1.0
										},
										"spreadFactor": 0.0,
										"translation": {
											"x": 0.0,
											"y": 0.0,
											"z": 2.6912198066711426
										},
										"type": "unary"
									},
									"index": 16,
									"mirrored": false,
									"name": "One Side Blend",
									"operator": "One_side_blend",
									"optionalCurve": {
										"closed": false,
										"points": []
									},
									"positionalB": "FIXED_POS",
									"type": "compose",
									"useIntersection": false
								},
								"composableB": {
									"composableA": {
										"densityValue": 1.5,
										"dimensions": {
											"x": 15.600000381469727,
											"y": 15.100000381469727,
											"z": 21.399999618530273
										},
										"index": 15,
										"material": "ROCK",
										"mirrored": false,
										"name": "Block",
										"optionalCurve": {
											"closed": false,
											"points": []
										},
										"position": {
											"x": 21.120662689208984,
											"y": 41.54602813720703,
											"z": 0.0
										},
										"shape": "Block",
										"sigmaValue": 5.0,
										"supportDimensions": {
											"x": 0.0,
											"y": 0.0,
											"z": 0.0
										},
										"type": "primitive"
									},
									"distortion": {
										"x": 0.0,
										"y": 0.0,
										"z": 0.0
									},
									"index": 14,
									"mirrored": false,
									"name": "",
									"noise": {
										"x": 0.0,
										"y": 0.0,
										"z": 0.0
									},
									"optionalCurve": {
										"closed": false,
										"points": []
									},
									"rotation": {
										"x": 0.0,
										"y": 0.0,
										"z": 0.0
									},
									"scale": {
										"x": 1.0,
										"y": 1.0,
										"z": 1.0
									},
									"spreadFactor": 0.0,
									"translation": {
										"x": 0.0,
										"y": 0.0,
										"z": 2.5872602462768555
									},
									"type": "unary"
								},
								"index": 13,
								"mirrored": false,
								"name": "One Side Blend",
								"operator": "One_side_blend",
								"optionalCurve": {
									"closed": false,
									"points": []
								},
								"positionalB": "FIXED_POS",
								"type": "compose",
								"useIntersection": false
							},
							"composableB": {
								"composableA": {
									"densityValue": -2.5,
									"dimensions": {
										"x": 15.600000381469727,
										"y": 15.100000381469727,
										"z": 21.399999618530273
									},
									"index": 12,
									"material": "WATER",
									"mirrored": false,
									"name": "Block",
									"optionalCurve": {
										"closed": false,
										"points": []
									},
									"position": {
										"x": 49.0526008605957,
										"y": 39.514488220214844,
										"z": 0.0
									},
									"shape": "Block",
									"sigmaValue": 5.0,
									"supportDimensions": {
										"x": 0.0,
										"y": 0.0,
										"z": 0.0
									},
									"type": "primitive"
								},
								"distortion": {
									"x": 0.0,
									"y": 0.0,
									"z": 0.0
								},
								"index": 11,
								"mirrored": false,
								"name": "",
								"noise": {
									"x": 0.0,
									"y": 0.0,
									"z": 0.0
								},
								"optionalCurve": {
									"closed": false,
									"points": []
								},
								"rotation": {
									"x": 0.0,
									"y": 0.0,
									"z": 0.0
								},
								"scale": {
									"x": 1.0,
									"y": 1.0,
									"z": 1.0
								},
								"spreadFactor": 0.0,
								"translation": {
									"x": 0.0,
									"y": 0.0,
									"z": 3.3516149520874023
								},
								"type": "unary"
							},
							"index": 10,
							"mirrored": false,
							"name": "One Side Blend",
							"operator": "One_side_blend",
							"optionalCurve": {
								"closed": false,
								"points": []
							},
							"positionalB": "FIXED_POS",
							"type": "compose",
							"useIntersection": false
						},
						"composableB": {
							"composableA": {
								"densityValue": -2.5,
								"dimensions": {
									"x": 15.600000381469727,
									"y": 15.100000381469727,
									"z": 21.399999618530273
								},
								"index": 9,
								"material": "WATER",
								"mirrored": false,
								"name": "Block",
								"optionalCurve": {
									"closed": false,
									"points": []
								},
								"position": {
									"x": 26.320392608642578,
									"y": 54.825172424316406,
									"z": 0.0
								},
								"shape": "Block",
								"sigmaValue": 5.0,
								"supportDimensions": {
									"x": 0.0,
									"y": 0.0,
									"z": 0.0
								},
								"type": "primitive"
							},
							"distortion": {
								"x": 0.0,
								"y": 0.0,
								"z": 0.0
							},
							"index": 8,
							"mirrored": false,
							"name": "",
							"noise": {
								"x": 0.0,
								"y": 0.0,
								"z": 0.0
							},
							"optionalCurve": {
								"closed": false,
								"points": []
							},
							"rotation": {
								"x": 0.0,
								"y": 0.0,
								"z": 0.0
							},
							"scale": {
								"x": 1.0,
								"y": 1.0,
								"z": 1.0
							},
							"spreadFactor": 0.0,
							"translation": {
								"x": 0.0,
								"y": 0.0,
								"z": 2.599236488342285
							},
							"type": "unary"
						},
						"index": 7,
						"mirrored": false,
						"name": "Blend",
						"operator": "Blend",
						"optionalCurve": {
							"closed": false,
							"points": []
						},
						"positionalB": "FIXED_POS",
						"type": "compose",
						"useIntersection": false
					},
					"composableB": {
						"composableA": {
							"densityValue": -2.5,
							"dimensions": {
								"x": 15.600000381469727,
								"y": 15.100000381469727,
								"z": 21.399999618530273
							},
							"index": 6,
							"material": "WATER",
							"mirrored": false,
							"name": "Block",
							"optionalCurve": {
								"closed": false,
								"points": []
							},
							"position": {
								"x": 34.83676528930664,
								"y": 55.219608306884766,
								"z": 0.0
							},
							"shape": "Block",
							"sigmaValue": 5.0,
							"supportDimensions": {
								"x": 0.0,
								"y": 0.0,
								"z": 0.0
							},
							"type": "primitive"
						},
						"distortion": {
							"x": 0.0,
							"y": 0.0,
							"z": 0.0
						},
						"index": 5,
						"mirrored": false,
						"name": "",
						"noise": {
							"x": 0.0,
							"y": 0.0,
							"z": 0.0
						},
						"optionalCurve": {
							"closed": false,
							"points": []
						},
						"rotation": {
							"x": 0.0,
							"y": 0.0,
							"z": 0.0
						},
						"scale": {
							"x": 1.0,
							"y": 1.0,
							"z": 1.0
						},
						"spreadFactor": 0.0,
						"translation": {
							"x": 0.0,
							"y": 0.0,
							"z": 2.6514315605163574
						},
						"type": "unary"
					},
					"index": 4,
					"mirrored": false,
					"name": "Blend",
					"operator": "Blend",
					"optionalCurve": {
						"closed": false,
						"points": []
					},
					"positionalB": "FIXED_POS",
					"type": "compose",
					"useIntersection": false
				},
				"composableB": {
					"composableA": {
						"densityValue": -2.5,
						"dimensions": {
							"x": 15.600000381469727,
							"y": 15.100000381469727,
							"z": 21.399999618530273
						},
						"index": 3,
						"material": "WATER",
						"mirrored": false,
						"name": "Block",
						"optionalCurve": {
							"closed": false,
							"points": []
						},
						"position": {
							"x": 43.6816520690918,
							"y": 56.99159622192383,
							"z": 0.0
						},
						"shape": "Block",
						"sigmaValue": 5.0,
						"supportDimensions": {
							"x": 0.0,
							"y": 0.0,
							"z": 0.0
						},
						"type": "primitive"
					},
					"distortion": {
						"x": 0.0,
						"y": 0.0,
						"z": 0.0
					},
					"index": 2,
					"mirrored": false,
					"name": "",
					"noise": {
						"x": 0.0,
						"y": 0.0,
						"z": 0.0
					},
					"optionalCurve": {
						"closed": false,
						"points": []
					},
					"rotation": {
						"x": 0.0,
						"y": 0.0,
						"z": 0.0
					},
					"scale": {
						"x": 1.0,
						"y": 1.0,
						"z": 1.0
					},
					"spreadFactor": 0.0,
					"translation": {
						"x": 0.0,
						"y": 0.0,
						"z": 2.1638541221618652
					},
					"type": "unary"
				},
				"index": 1,
				"mirrored": false,
				"name": "Blend",
				"operator": "Blend",
				"optionalCurve": {
					"closed": false,
					"points": []
				},
				"positionalB": "FIXED_POS",
				"type": "compose",
				"useIntersection": false
			}
		],
		"index": 0,
		"mirrored": false,
		"name": "",
		"optionalCurve": {
			"closed": false,
			"points": []
		},
		"type": "compose"
	}
}