<!DOCTYPE QGLVIEWER>
<QGLViewer version="2.6.3">
  <State stereo="false">
    <foregroundColor red="180" blue="180" green="180"/>
    <backgroundColor red="127" blue="127" green="127"/>
  </State>
  <Display axisIsDrawn="false" FPSIsDisplayed="false" gridIsDrawn="false" cameraIsEdited="false"/>
  <Geometry posX="72" width="1848" fullScreen="false" height="1016" posY="27"/>
  <Camera>
    <Parameters fieldOfView="0.785398" zNearCoefficient="0.005" Type="PERSPECTIVE" sceneRadius="500" zClippingCoefficient="1.73205" orthoCoef="0">
      <SceneCenter y="50" x="50" z="20"/>
    </Parameters>
    <Stereo physScreenWidth="0.5" focusDistance="1207.11" IODist="0.062"/>
    <ManipulatedCameraFrame>
      <position y="126.525" x="58.6367" z="80.3499"/>
      <orientation q2="0.858283" q1="0.483843" q0="0.138481" q3="0.100343"/>
      <ManipulatedParameters spinSens="0.3" rotSens="1" wheelSens="1" zoomSens="1" transSens="1"/>
      <ManipulatedCameraParameters flySpeed="5" zoomsOnPivotPoint="false" rotatesAroundUpVector="false">
        <sceneUpVector y="1" x="0" z="0"/>
      </ManipulatedCameraParameters>
    </ManipulatedCameraFrame>
  </Camera>
</QGLViewer>
